[
{"charsetinfo": {"name": "utf-8"}},
{
"history": [
{
	"metadata": {
		"BOARDID": {"type": "string", "bytes": 12, "max_size": 0},
		"TRADEDATE": {"type": "date", "bytes": 10, "max_size": 0},
		"SHORTNAME": {"type": "string", "bytes": 189, "max_size": 0},
		"SECID": {"type": "string", "bytes": 36, "max_size": 0},
		"OPEN": {"type": "double"},
		"LOW": {"type": "double"},
		"HIGH": {"type": "double"},
		"CLOSE": {"type": "double"},
		"NUMTRADES": {"type": "double"},
		"VOLRUR": {"type": "double"},
		"WAPRICE": {"type": "double"}
	}
},
[
{"BOARDID": "CETS", "TRADEDATE": "2023-08-01", "SHORTNAME": "PLDRUB_TOD", "SECID": "PLDRUB_TOD", "OPEN": 0, "LOW": 0, "HIGH": 0, "CLOSE": 0, "NUMTRADES": 0, "VOLRUR": 0, "WAPRICE": null},
{"BOARDID": "CETS", "TRADEDATE": "2023-08-01", "SHORTNAME": "PLDRUB_TOM", "SECID": "PLDRUB_TOM", "OPEN": 0, "LOW": 0, "HIGH": 0, "CLOSE": 0, "NUMTRADES": 0, "VOLRUR": 0, "WAPRICE": null},
{"BOARDID": "CETS", "TRADEDATE": "2023-08-01", "SHORTNAME": "PLD_TOMSPT", "SECID": "PLDRUB_TOM1D", "OPEN": 0, "LOW": 0, "HIGH": 0, "CLOSE": 0, "NUMTRADES": 0, "VOLRUR": 0, "WAPRICE": null},
{"BOARDID": "CETS", "TRADEDATE": "2023-08-01", "SHORTNAME": "PLD_TOM1M", "SECID": "PLDRUB_TOM1M", "OPEN": 0, "LOW": 0, "HIGH": 0, "CLOSE": 0, "NUMTRADES": 0, "VOLRUR": 0, "WAPRICE": null},
{"BOARDID": "CETS", "TRADEDATE": "2023-08-01", "SHORTNAME": "PLD_TOM1W", "SECID": "PLDRUB_TOM1W", "OPEN": 0, "LOW": 0, "HIGH": 0, "CLOSE": 0, "NUMTRADES": 0, "VOLRUR": 0, "WAPRICE": null},
{"BOARDID": "CETS", "TRADEDATE": "2023-08-01", "SHORTNAME": "PLD_TOM6M", "SECID": "PLDRUB_TOM6M", "OPEN": 0, "LOW": 0, "HIGH": 0, "CLOSE": 0, "NUMTRADES": 0, "VOLRUR": 0, "WAPRICE": null},
{"BOARDID": "CETS", "TRADEDATE": "2023-08-01", "SHORTNAME": "PLT_TODTOM", "SECID": "PLTRUBTODTOM", "OPEN": 0, "LOW": 0, "HIGH": 0, "CLOSE": 0, "NUMTRADES": 0, "VOLRUR": 0, "WAPRICE": null},
{"BOARDID": "CETS", "TRADEDATE": "2023-08-01", "SHORTNAME": "PLTRUB_LTV", "SECID": "PLTRUB_FWD", "OPEN": 0, "LOW": 0, "HIGH": 0, "CLOSE": 0, "NUMTRADES": 0, "VOLRUR": 0, "WAPRICE": null},
{"BOARDID": "CETS", "TRADEDATE": "2023-08-01", "SHORTNAME": "PLTRUB_SPT", "SECID": "PLTRUB_SPT", "OPEN": 0, "LOW": 0, "HIGH": 0, "CLOSE": 0, "NUMTRADES": 0, "VOLRUR": 0, "WAPRICE": null},
{"BOARDID": "CETS", "TRADEDATE": "2023-08-01", "SHORTNAME": "PLTRUB_TOD", "SECID": "PLTRUB_TOD", "OPEN": 0, "LOW": 0, "HIGH": 0, "CLOSE": 0, "NUMTRADES": 0, "VOLRUR": 0, "WAPRICE": null},
{"BOARDID": "CETS", "TRADEDATE": "2023-08-01", "SHORTNAME": "PLTRUB_TOM", "SECID": "PLTRUB_TOM", "OPEN": 0, "LOW": 0, "HIGH": 0, "CLOSE": 0, "NUMTRADES": 0, "VOLRUR": 0, "WAPRICE": null},
{"BOARDID": "CETS", "TRADEDATE": "2023-08-01", "SHORTNAME": "PLT_TOMSPT", "SECID": "PLTRUB_TOM1D", "OPEN": 0, "LOW": 0, "HIGH": 0, "CLOSE": 0, "NUMTRADES": 0, "VOLRUR": 0, "WAPRICE": null},
{"BOARDID": "CETS", "TRADEDATE": "2023-08-01", "SHORTNAME": "PLT_TOM1M", "SECID": "PLTRUB_TOM1M", "OPEN": 0, "LOW": 0, "HIGH": 0, "CLOSE": 0, "NUMTRADES": 0, "VOLRUR": 0, "WAPRICE": null},
{"BOARDID": "CETS", "TRADEDATE": "2023-08-01", "SHORTNAME": "PLT_TOM1W", "SECID": "PLTRUB_TOM1W", "OPEN": 0, "LOW": 0, "HIGH": 0, "CLOSE": 0, "NUMTRADES": 0, "VOLRUR": 0, "WAPRICE": null},
{"BOARDID": "CETS", "TRADEDATE": "2023-08-01", "SHORTNAME": "PLT_TOM6M", "SECID": "PLTRUB_TOM6M", "OPEN": 0, "LOW": 0, "HIGH": 0, "CLOSE": 0, "NUMTRADES": 0, "VOLRUR": 0, "WAPRICE": null},
{"BOARDID": "CETS", "TRADEDATE": "2023-08-01", "SHORTNAME": "SLV_TODTOM", "SECID": "SLVRUBTODTOM", "OPEN": 0, "LOW": 0, "HIGH": 0, "CLOSE": 0, "NUMTRADES": 0, "VOLRUR": 0, "WAPRICE": null},
{"BOARDID": "CETS", "TRADEDATE": "2023-08-01", "SHORTNAME": "SLVRUB_LTV", "SECID": "SLVRUB_FWD", "OPEN": 0, "LOW": 0, "HIGH": 0, "CLOSE": 0, "NUMTRADES": 0, "VOLRUR": 0, "WAPRICE": null},
{"BOARDID": "CETS", "TRADEDATE": "2023-08-01", "SHORTNAME": "SLVRUB_SPT", "SECID": "SLVRUB_SPT", "OPEN": 0, "LOW": 0, "HIGH": 0, "CLOSE": 0, "NUMTRADES": 0, "VOLRUR": 0, "WAPRICE": null},
{"BOARDID": "CETS", "TRADEDATE": "2023-08-01", "SHORTNAME": "SLVRUB_TOD", "SECID": "SLVRUB_TOD", "OPEN": 0, "LOW": 0, "HIGH": 0, "CLOSE": 0, "NUMTRADES": 0, "VOLRUR": 0, "WAPRICE": null},
{"BOARDID": "CETS", "TRADEDATE": "2023-08-01", "SHORTNAME": "SLVRUB_TOM", "SECID": "SLVRUB_TOM", "OPEN": 73.49, "LOW": 73.35, "HIGH": 77.15, "CLOSE": 74.34, "NUMTRADES": 1237, "VOLRUR": 51294085, "WAPRICE": 74.4},
{"BOARDID": "CETS", "TRADEDATE": "2023-08-01", "SHORTNAME": "SLV_TOMSPT", "SECID": "SLVRUB_TOM1D", "OPEN": 0, "LOW": 0, "HIGH": 0, "CLOSE": 0, "NUMTRADES": 0, "VOLRUR": 0, "WAPRICE": null},
{"BOARDID": "CETS", "TRADEDATE": "2023-08-01", "SHORTNAME": "SLV_TOM1M", "SECID": "SLVRUB_TOM1M", "OPEN": 0, "LOW": 0, "HIGH": 0, "CLOSE": 0, "NUMTRADES": 0, "VOLRUR": 0, "WAPRICE": null},
{"BOARDID": "CETS", "TRADEDATE": "2023-08-01", "SHORTNAME": "SLV_TOM1W", "SECID": "SLVRUB_TOM1W", "OPEN": 0, "LOW": 0, "HIGH": 0, "CLOSE": 0, "NUMTRADES": 0, "VOLRUR": 0, "WAPRICE": null},
{"BOARDID": "CETS", "TRADEDATE": "2023-08-01", "SHORTNAME": "SLV_TOM6M", "SECID": "SLVRUB_TOM6M", "OPEN": 0, "LOW": 0, "HIGH": 0, "CLOSE": 0, "NUMTRADES": 0, "VOLRUR": 0, "WAPRICE": null},
{"BOARDID": "CETS", "TRADEDATE": "2023-08-01", "SHORTNAME": "TJS_TODTOM", "SECID": "TJSRUBTODTOM", "OPEN": 0, "LOW": 0, "HIGH": 0, "CLOSE": 0, "NUMTRADES": 0, "VOLRUR": 0, "WAPRICE": null},
{"BOARDID": "CETS", "TRADEDATE": "2023-08-01", "SHORTNAME": "TJSRUB_TOD", "SECID": "TJSRUB_TOD", "OPEN": 0, "LOW": 0, "HIGH": 0, "CLOSE": 0, "NUMTRADES": 0, "VOLRUR": 0, "WAPRICE": null},
{"BOARDID": "CETS", "TRADEDATE": "2023-08-01", "SHORTNAME": "TJSRUB_TOM", "SECID": "TJSRUB_TOM", "OPEN": 0, "LOW": 0, "HIGH": 0, "CLOSE": 0, "NUMTRADES": 0, "VOLRUR": 0, "WAPRICE": null},
{"BOARDID": "CETS", "TRADEDATE": "2023-08-01", "SHORTNAME": "TRY_TODTOM", "SECID": "TRYRUBTODTOM", "OPEN": 0, "LOW": 0, "HIGH": 0, "CLOSE": 0, "NUMTRADES": 0, "VOLRUR": 0, "WAPRICE": null},
{"BOARDID": "CETS", "TRADEDATE": "2023-08-01", "SHORTNAME": "TRYRUB_TMS", "SECID": "TRYRUB_TMS", "OPEN": 0, "LOW": 0, "HIGH": 0, "CLOSE": 0, "NUMTRADES": 0, "VOLRUR": 0, "WAPRICE": null},
{"BOARDID": "CETS", "TRADEDATE": "2023-08-01", "SHORTNAME": "TRYRUB_TOD", "SECID": "TRYRUB_TOD", "OPEN": 3.4, "LOW": 3.39, "HIGH": 3.4, "CLOSE": 3.4, "NUMTRADES": 4, "VOLRUR": 928893, "WAPRICE": 3.3901},
{"BOARDID": "CETS", "TRADEDATE": "2023-08-01", "SHORTNAME": "TRYRUB_TOM", "SECID": "TRYRUB_TOM", "OPEN": 3.4, "LOW": 3.393, "HIGH": 3.439, "CLOSE": 3.438, "NUMTRADES": 2946, "VOLRUR": 1864863837, "WAPRICE": 3.4138},
{"BOARDID": "CETS", "TRADEDATE": "2023-08-01", "SHORTNAME": "USDRUB_TOD", "SECID": "USD000000TOD", "OPEN": 91.695, "LOW": 91.4675, "HIGH": 92.25, "CLOSE": 92.21, "NUMTRADES": 7204, "VOLRUR": 34941484570, "WAPRICE": 91.795},
{"BOARDID": "CETS", "TRADEDATE": "2023-08-01", "SHORTNAME": "USD_TODTOM", "SECID": "USD000TODTOM", "OPEN": -0.02, "LOW": -0.0552, "HIGH": 0.0237, "CLOSE": 0.0205, "NUMTRADES": 953, "VOLRUR": 125283821110, "WAPRICE": -0.0242},
{"BOARDID": "CETS", "TRADEDATE": "2023-08-01", "SHORTNAME": "USDRUB_TOM", "SECID": "USD000UTSTOM", "OPEN": 91.695, "LOW": 91.4175, "HIGH": 92.49, "CLOSE": 92.33, "NUMTRADES": 15887, "VOLRUR": 72727623677.5, "WAPRICE": 91.8769},
{"BOARDID": "CETS", "TRADEDATE": "2023-08-01", "SHORTNAME": "USDAEDTDTM", "SECID": "USDAEDTODTOM", "OPEN": 0, "LOW": 0, "HIGH": 0, "CLOSE": 0, "NUMTRADES": 0, "VOLRUR": 0, "WAPRICE": null},
{"BOARDID": "CETS", "TRADEDATE": "2023-08-01", "SHORTNAME": "USDAED_TOD", "SECID": "USDAED_TOD", "OPEN": 0, "LOW": 0, "HIGH": 0, "CLOSE": 0, "NUMTRADES": 0, "VOLRUR": 0, "WAPRICE": null},
{"BOARDID": "CETS", "TRADEDATE": "2023-08-01", "SHORTNAME": "USDAED_TOM", "SECID": "USDAED_TOM", "OPEN": 0, "LOW": 0, "HIGH": 0, "CLOSE": 0, "NUMTRADES": 0, "VOLRUR": 0, "WAPRICE": null},
{"BOARDID": "CETS", "TRADEDATE": "2023-08-01", "SHORTNAME": "USDAMDTDTM", "SECID": "USDAMDTODTOM", "OPEN": 0, "LOW": 0, "HIGH": 0, "CLOSE": 0, "NUMTRADES": 0, "VOLRUR": 0, "WAPRICE": null},
{"BOARDID": "CETS", "TRADEDATE": "2023-08-01", "SHORTNAME": "USDAMD_TOD", "SECID": "USDAMD_TOD", "OPEN": 0, "LOW": 0, "HIGH": 0, "CLOSE": 0, "NUMTRADES": 0, "VOLRUR": 0, "WAPRICE": null},
{"BOARDID": "CETS", "TRADEDATE": "2023-08-01", "SHORTNAME": "USDAMD_TOM", "SECID": "USDAMD_TOM", "OPEN": 383.5, "LOW": 383.5, "HIGH": 383.5, "CLOSE": 383.5, "NUMTRADES": 1, "VOLRUR": 9096620, "WAPRICE": 383.5},
{"BOARDID": "CETS", "TRADEDATE": "2023-08-01", "SHORTNAME": "USDCHFTDTM", "SECID": "USDCHFTODTOM", "OPEN": 0, "LOW": 0, "HIGH": 0, "CLOSE": 0, "NUMTRADES": 0, "VOLRUR": 0, "WAPRICE": null},
{"BOARDID": "CETS", "TRADEDATE": "2023-08-01", "SHORTNAME": "USDCHF_SPT", "SECID": "USDCHF_SPT", "OPEN": 0, "LOW": 0, "HIGH": 0, "CLOSE": 0, "NUMTRADES": 0, "VOLRUR": 0, "WAPRICE": null},
{"BOARDID": "CETS", "TRADEDATE": "2023-08-01", "SHORTNAME": "USDCHF_TOD", "SECID": "USDCHF_TOD", "OPEN": 0, "LOW": 0, "HIGH": 0, "CLOSE": 0, "NUMTRADES": 0, "VOLRUR": 0, "WAPRICE": null},
{"BOARDID": "CETS", "TRADEDATE": "2023-08-01", "SHORTNAME": "USDCHF_TOM", "SECID": "USDCHF_TOM", "OPEN": 0, "LOW": 0, "HIGH": 0, "CLOSE": 0, "NUMTRADES": 0, "VOLRUR": 0, "WAPRICE": null},
{"BOARDID": "CETS", "TRADEDATE": "2023-08-01", "SHORTNAME": "USDCHFTMSP", "SECID": "USDCHF_TOM1D", "OPEN": 0, "LOW": 0, "HIGH": 0, "CLOSE": 0, "NUMTRADES": 0, "VOLRUR": 0, "WAPRICE": null},
{"BOARDID": "CETS", "TRADEDATE": "2023-08-01", "SHORTNAME": "USDCNYTDTM", "SECID": "USDCNYTODTOM", "OPEN": 0, "LOW": 0, "HIGH": 0, "CLOSE": 0, "NUMTRADES": 0, "VOLRUR": 0, "WAPRICE": null},
{"BOARDID": "CETS", "TRADEDATE": "2023-08-01", "SHORTNAME": "USDCNY_SPT", "SECID": "USDCNY_SPT", "OPEN": 0, "LOW": 0, "HIGH": 0, "CLOSE": 0, "NUMTRADES": 0, "VOLRUR": 0, "WAPRICE": null},
{"BOARDID": "CETS", "TRADEDATE": "2023-08-01", "SHORTNAME": "USDCNY_TOD", "SECID": "USDCNY_TOD", "OPEN": 7.1701, "LOW": 7.1701, "HIGH": 7.182, "CLOSE": 7.174, "NUMTRADES": 26, "VOLRUR": 220691580.03, "WAPRICE": 7.17786},
{"BOARDID": "CETS", "TRADEDATE": "2023-08-01", "SHORTNAME": "USDCNY_TOM", "SECID": "USDCNY_TOM", "OPEN": 7.1605, "LOW": 7.1605, "HIGH": 7.1987, "CLOSE": 7.1987, "NUMTRADES": 3520, "VOLRUR": 30983132327.84, "WAPRICE": 7.17864},
{"BOARDID": "CETS", "TRADEDATE": "2023-08-01", "SHORTNAME": "USDCNYTMSP", "SECID": "USDCNY_TOM1D", "OPEN": 0, "LOW": 0, "HIGH": 0, "CLOSE": 0, "NUMTRADES": 0, "VOLRUR": 0, "WAPRICE": null},
{"BOARDID": "CETS", "TRADEDATE": "2023-08-01", "SHORTNAME": "USDJPYTDTM", "SECID": "USDJPYTODTOM", "OPEN": 0, "LOW": 0, "HIGH": 0, "CLOSE": 0, "NUMTRADES": 0, "VOLRUR": 0, "WAPRICE": null},
{"BOARDID": "CETS", "TRADEDATE": "2023-08-01", "SHORTNAME": "USDJPY_SPT", "SECID": "USDJPY_SPT", "OPEN": 0, "LOW": 0, "HIGH": 0, "CLOSE": 0, "NUMTRADES": 0, "VOLRUR": 0, "WAPRICE": null},
{"BOARDID": "CETS", "TRADEDATE": "2023-08-01", "SHORTNAME": "USDJPY_TOD", "SECID": "USDJPY_TOD", "OPEN": 0, "LOW": 0, "HIGH": 0, "CLOSE": 0, "NUMTRADES": 0, "VOLRUR": 0, "WAPRICE": null},
{"BOARDID": "CETS", "TRADEDATE": "2023-08-01", "SHORTNAME": "USDJPY_TOM", "SECID": "USDJPY_TOM", "OPEN": 0, "LOW": 0, "HIGH": 0, "CLOSE": 0, "NUMTRADES": 0, "VOLRUR": 0, "WAPRICE": null},
{"BOARDID": "CETS", "TRADEDATE": "2023-08-01", "SHORTNAME": "USDJPYTMSP", "SECID": "USDJPY_TOM1D", "OPEN": 0, "LOW": 0, "HIGH": 0, "CLOSE": 0, "NUMTRADES": 0, "VOLRUR": 0, "WAPRICE": null},
{"BOARDID": "CETS", "TRADEDATE": "2023-08-01", "SHORTNAME": "USDKZTTDTM", "SECID": "USDKZTTODTOM", "OPEN": 0, "LOW": 0, "HIGH": 0, "CLOSE": 0, "NUMTRADES": 0, "VOLRUR": 0, "WAPRICE": null},
{"BOARDID": "CETS", "TRADEDATE": "2023-08-01", "SHORTNAME": "USDKZT_SPT", "SECID": "USDKZT_SPT", "OPEN": 0, "LOW": 0, "HIGH": 0, "CLOSE": 0, "NUMTRADES": 0, "VOLRUR": 0, "WAPRICE": null},
{"BOARDID": "CETS", "TRADEDATE": "2023-08-01", "SHORTNAME": "USDKZT_TOD", "SECID": "USDKZT_TOD", "OPEN": 0, "LOW": 0, "HIGH": 0, "CLOSE": 0, "NUMTRADES": 0, "VOLRUR": 0, "WAPRICE": null},
{"BOARDID": "CETS", "TRADEDATE": "2023-08-01", "SHORTNAME": "USDKZT_TOM", "SECID": "USDKZT_TOM", "OPEN": 444.2, "LOW": 443.95, "HIGH": 445.99, "CLOSE": 443.95, "NUMTRADES": 223, "VOLRUR": 1220214891.61, "WAPRICE": 444.62},
{"BOARDID": "CETS", "TRADEDATE": "2023-08-01", "SHORTNAME": "USDKZTTMSP", "SECID": "USDKZT_TOM1D", "OPEN": 0, "LOW": 0, "HIGH": 0, "CLOSE": 0, "NUMTRADES": 0, "VOLRUR": 0, "WAPRICE": null},
{"BOARDID": "CETS", "TRADEDATE": "2023-08-01", "SHORTNAME": "USDRUB_DIS", "SECID": "USDRUB_DIS", "OPEN": null, "LOW": null, "HIGH": null, "CLOSE": null, "NUMTRADES": 0, "VOLRUR": 0, "WAPRICE": null},
{"BOARDID": "CETS", "TRADEDATE": "2023-08-01", "SHORTNAME": "USDRUB_LTV", "SECID": "USDRUB_FWD", "OPEN": 0, "LOW": 0, "HIGH": 0, "CLOSE": 0, "NUMTRADES": 0, "VOLRUR": 0, "WAPRICE": null},
{"BOARDID": "CETS", "TRADEDATE": "2023-08-01", "SHORTNAME": "USDRUB_SPT", "SECID": "USDRUB_SPT", "OPEN": 0, "LOW": 0, "HIGH": 0, "CLOSE": 0, "NUMTRADES": 0, "VOLRUR": 0, "WAPRICE": null},
{"BOARDID": "CETS", "TRADEDATE": "2023-08-01", "SHORTNAME": "USDRUB_TMS", "SECID": "USDRUB_TMS", "OPEN": 91.7075, "LOW": 91.0025, "HIGH": 92.4, "CLOSE": 92.2225, "NUMTRADES": 3025, "VOLRUR": 48230766.12, "WAPRICE": 91.8398},
{"BOARDID": "CETS", "TRADEDATE": "2023-08-01", "SHORTNAME": "USD_TOMSPT", "SECID": "USDRUB_TOM1D", "OPEN": 0, "LOW": 0, "HIGH": 0, "CLOSE": 0, "NUMTRADES": 0, "VOLRUR": 0, "WAPRICE": null},
{"BOARDID": "CETS", "TRADEDATE": "2023-08-01", "SHORTNAME": "USD_TOM1M", "SECID": "USDRUB_TOM1M", "OPEN": 0, "LOW": 0, "HIGH": 0, "CLOSE": 0, "NUMTRADES": 0, "VOLRUR": 0, "WAPRICE": null},
{"BOARDID": "CETS", "TRADEDATE": "2023-08-01", "SHORTNAME": "USD_TOM1W", "SECID": "USDRUB_TOM1W", "OPEN": 0, "LOW": 0, "HIGH": 0, "CLOSE": 0, "NUMTRADES": 0, "VOLRUR": 0, "WAPRICE": null},
{"BOARDID": "CETS", "TRADEDATE": "2023-08-01", "SHORTNAME": "USD_TOM1Y", "SECID": "USDRUB_TOM1Y", "OPEN": 0, "LOW": 0, "HIGH": 0, "CLOSE": 0, "NUMTRADES": 0, "VOLRUR": 0, "WAPRICE": null},
{"BOARDID": "CETS", "TRADEDATE": "2023-08-01", "SHORTNAME": "USD_TOM2M", "SECID": "USDRUB_TOM2M", "OPEN": 0, "LOW": 0, "HIGH": 0, "CLOSE": 0, "NUMTRADES": 0, "VOLRUR": 0, "WAPRICE": null},
{"BOARDID": "CETS", "TRADEDATE": "2023-08-01", "SHORTNAME": "USD_TOM2W", "SECID": "USDRUB_TOM2W", "OPEN": 0, "LOW": 0, "HIGH": 0, "CLOSE": 0, "NUMTRADES": 0, "VOLRUR": 0, "WAPRICE": null},
{"BOARDID": "CETS", "TRADEDATE": "2023-08-01", "SHORTNAME": "USD_TOM3M", "SECID": "USDRUB_TOM3M", "OPEN": 0, "LOW": 0, "HIGH": 0, "CLOSE": 0, "NUMTRADES": 0, "VOLRUR": 0, "WAPRICE": null},
{"BOARDID": "CETS", "TRADEDATE": "2023-08-01", "SHORTNAME": "USD_TOM6M", "SECID": "USDRUB_TOM6M", "OPEN": 0, "LOW": 0, "HIGH": 0, "CLOSE": 0, "NUMTRADES": 0, "VOLRUR": 0, "WAPRICE": null},
{"BOARDID": "CETS", "TRADEDATE": "2023-08-01", "SHORTNAME": "USD_TOM9M", "SECID": "USDRUB_TOM9M", "OPEN": 0, "LOW": 0, "HIGH": 0, "CLOSE": 0, "NUMTRADES": 0, "VOLRUR": 0, "WAPRICE": null},
{"BOARDID": "CETS", "TRADEDATE": "2023-08-01", "SHORTNAME": "USDTRYTDTM", "SECID": "USDTRYTODTOM", "OPEN": 0, "LOW": 0, "HIGH": 0, "CLOSE": 0, "NUMTRADES": 0, "VOLRUR": 0, "WAPRICE": null},
{"BOARDID": "CETS", "TRADEDATE": "2023-08-01", "SHORTNAME": "USDTRY_SPT", "SECID": "USDTRY_SPT", "OPEN": 0, "LOW": 0, "HIGH": 0, "CLOSE": 0, "NUMTRADES": 0, "VOLRUR": 0, "WAPRICE": null},
{"BOARDID": "CETS", "TRADEDATE": "2023-08-01", "SHORTNAME": "USDTRY_TOD", "SECID": "USDTRY_TOD", "OPEN": 0, "LOW": 0, "HIGH": 0, "CLOSE": 0, "NUMTRADES": 0, "VOLRUR": 0, "WAPRICE": null},
{"BOARDID": "CETS", "TRADEDATE": "2023-08-01", "SHORTNAME": "USDTRY_TOM", "SECID": "USDTRY_TOM", "OPEN": 0, "LOW": 0, "HIGH": 0, "CLOSE": 0, "NUMTRADES": 0, "VOLRUR": 0, "WAPRICE": null},
{"BOARDID": "CETS", "TRADEDATE": "2023-08-01", "SHORTNAME": "USDTRYTMSP", "SECID": "USDTRY_TOM1D", "OPEN": 0, "LOW": 0, "HIGH": 0, "CLOSE": 0, "NUMTRADES": 0, "VOLRUR": 0, "WAPRICE": null},
{"BOARDID": "CETS", "TRADEDATE": "2023-08-01", "SHORTNAME": "USDZARTDTM", "SECID": "USDZARTODTOM", "OPEN": 0, "LOW": 0, "HIGH": 0, "CLOSE": 0, "NUMTRADES": 0, "VOLRUR": 0, "WAPRICE": null},
{"BOARDID": "CETS", "TRADEDATE": "2023-08-01", "SHORTNAME": "USDZAR_TOD", "SECID": "USDZAR_TOD", "OPEN": 0, "LOW": 0, "HIGH": 0, "CLOSE": 0, "NUMTRADES": 0, "VOLRUR": 0, "WAPRICE": null},
{"BOARDID": "CETS", "TRADEDATE": "2023-08-01", "SHORTNAME": "USDZAR_TOM", "SECID": "USDZAR_TOM", "OPEN": 0, "LOW": 0, "HIGH": 0, "CLOSE": 0, "NUMTRADES": 0, "VOLRUR": 0, "WAPRICE": null},
{"BOARDID": "CETS", "TRADEDATE": "2023-08-01", "SHORTNAME": "UZS_TODTOM", "SECID": "UZSRUBTODTOM", "OPEN": 0, "LOW": 0, "HIGH": 0, "CLOSE": 0, "NUMTRADES": 0, "VOLRUR": 0, "WAPRICE": null},
{"BOARDID": "CETS", "TRADEDATE": "2023-08-01", "SHORTNAME": "UZSRUB_TOD", "SECID": "UZSRUB_TOD", "OPEN": 0, "LOW": 0, "HIGH": 0, "CLOSE": 0, "NUMTRADES": 0, "VOLRUR": 0, "WAPRICE": null},
{"BOARDID": "CETS", "TRADEDATE": "2023-08-01", "SHORTNAME": "UZSRUB_TOM", "SECID": "UZSRUB_TOM", "OPEN": 79.575, "LOW": 76.0025, "HIGH": 79.5775, "CLOSE": 76.0025, "NUMTRADES": 8, "VOLRUR": 162814.75, "WAPRICE": 77.5308},
{"BOARDID": "CETS", "TRADEDATE": "2023-08-01", "SHORTNAME": "ZAR_TODTOM", "SECID": "ZARRUBTODTOM", "OPEN": 0, "LOW": 0, "HIGH": 0, "CLOSE": 0, "NUMTRADES": 0, "VOLRUR": 0, "WAPRICE": null},
{"BOARDID": "CETS", "TRADEDATE": "2023-08-01", "SHORTNAME": "ZARRUB_TMS", "SECID": "ZARRUB_TMS", "OPEN": 0, "LOW": 0, "HIGH": 0, "CLOSE": 0, "NUMTRADES": 0, "VOLRUR": 0, "WAPRICE": null},
{"BOARDID": "CETS", "TRADEDATE": "2023-08-01", "SHORTNAME": "ZARRUB_TOD", "SECID": "ZARRUB_TOD", "OPEN": 0, "LOW": 0, "HIGH": 0, "CLOSE": 0, "NUMTRADES": 0, "VOLRUR": 0, "WAPRICE": null},
{"BOARDID": "CETS", "TRADEDATE": "2023-08-01", "SHORTNAME": "ZARRUB_TOM", "SECID": "ZARRUB_TOM", "OPEN": 0, "LOW": 0, "HIGH": 0, "CLOSE": 0, "NUMTRADES": 0, "VOLRUR": 0, "WAPRICE": null}
]
],
"history.cursor": [
{
	"metadata": {
		"INDEX": {"type": "int64"},
		"TOTAL": {"type": "int64"},
		"PAGESIZE": {"type": "int64"}
	}
},
[
{"INDEX": 100, "TOTAL": 188, "PAGESIZE": 100}
]
]}
]