[
{"charsetinfo": {"name": "utf-8"}},
{
"history": [
{
	"metadata": {
		"BOARDID": {"type": "string", "bytes": 12, "max_size": 0},
		"TRADEDATE": {"type": "date", "bytes": 10, "max_size": 0},
		"SECID": {"type": "string", "bytes": 51, "max_size": 0},
		"OPEN": {"type": "double"},
		"LOW": {"type": "double"},
		"HIGH": {"type": "double"},
		"CLOSE": {"type": "double"},
		"OPENPOSITIONVALUE": {"type": "double"},
		"VALUE": {"type": "double"},
		"VOLUME": {"type": "int64"},
		"OPENPOSITION": {"type": "int64"},
		"SETTLEPRICE": {"type": "double"},
		"SWAPRATE": {"type": "double"},
		"WAPRICE": {"type": "double"},
		"SETTLEPRICEDAY": {"type": "double"},
		"CHANGE": {"type": "double"},
		"QTY": {"type": "int64"},
		"NUMTRADES": {"type": "int64"}
	}
},
[
{"BOARDID": "RFUD", "TRADEDATE": "2023-03-31", "SECID": "TTM3", "OPEN": 38021.00000, "LOW": 37200.00000, "HIGH": 38242.00000, "CLOSE": 37780.00000, "OPENPOSITIONVALUE": 173499000.00, "VALUE": 67348700.00, "VOLUME": 1786, "OPENPOSITION": 4596, "SETTLEPRICE": 37750.00000, "SWAPRATE": 0.00000, "WAPRICE": 37709.00000, "SETTLEPRICEDAY": 37276.00000, "CHANGE": -0.84000, "QTY": 1, "NUMTRADES": 1076},
{"BOARDID": "RFUD", "TRADEDATE": "2023-03-31", "SECID": "TTM3TTU3", "OPEN": null, "LOW": null, "HIGH": null, "CLOSE": null, "OPENPOSITIONVALUE": 0.00, "VALUE": null, "VOLUME": null, "OPENPOSITION": 0, "SETTLEPRICE": -500.00000, "SWAPRATE": null, "WAPRICE": null, "SETTLEPRICEDAY": -276.00000, "CHANGE": null, "QTY": null, "NUMTRADES": 0},
{"BOARDID": "RFUD", "TRADEDATE": "2023-03-31", "SECID": "TTU3", "OPEN": 37847.00000, "LOW": 37000.00000, "HIGH": 37847.00000, "CLOSE": 37000.00000, "OPENPOSITIONVALUE": 8940000.00, "VALUE": 485323.00, "VOLUME": 13, "OPENPOSITION": 240, "SETTLEPRICE": 37250.00000, "SWAPRATE": 0.00000, "WAPRICE": 37333.00000, "SETTLEPRICEDAY": 37000.00000, "CHANGE": -1.19000, "QTY": 1, "NUMTRADES": 11},
{"BOARDID": "RFUD", "TRADEDATE": "2023-03-31", "SECID": "TTZ3", "OPEN": null, "LOW": null, "HIGH": null, "CLOSE": null, "OPENPOSITIONVALUE": 0.00, "VALUE": null, "VOLUME": null, "OPENPOSITION": 0, "SETTLEPRICE": 38099.00000, "SWAPRATE": 0.00000, "WAPRICE": null, "SETTLEPRICEDAY": 38100.00000, "CHANGE": null, "QTY": null, "NUMTRADES": 0},
{"BOARDID": "RFUD", "TRADEDATE": "2023-03-31", "SECID": "TYH4", "OPEN": null, "LOW": null, "HIGH": null, "CLOSE": null, "OPENPOSITIONVALUE": 398520.00, "VALUE": null, "VOLUME": null, "OPENPOSITION": 108, "SETTLEPRICE": 3.69000, "SWAPRATE": 0.00000, "WAPRICE": null, "SETTLEPRICEDAY": 3.70600, "CHANGE": null, "QTY": null, "NUMTRADES": 0},
{"BOARDID": "RFUD", "TRADEDATE": "2023-03-31", "SECID": "TYM3", "OPEN": 3.94900, "LOW": 3.86000, "HIGH": 4.00200, "CLOSE": 3.96800, "OPENPOSITIONVALUE": 21228800.00, "VALUE": 4145184.00, "VOLUME": 1044, "OPENPOSITION": 5350, "SETTLEPRICE": 3.96800, "SWAPRATE": 0.00000, "WAPRICE": 3.97000, "SETTLEPRICEDAY": 3.95300, "CHANGE": 0.48000, "QTY": 25, "NUMTRADES": 57},
{"BOARDID": "RFUD", "TRADEDATE": "2023-03-31", "SECID": "TYM3TYU3", "OPEN": null, "LOW": null, "HIGH": null, "CLOSE": null, "OPENPOSITIONVALUE": 0.00, "VALUE": null, "VOLUME": null, "OPENPOSITION": 0, "SETTLEPRICE": -0.09700, "SWAPRATE": null, "WAPRICE": null, "SETTLEPRICEDAY": -0.01500, "CHANGE": null, "QTY": null, "NUMTRADES": 0},
{"BOARDID": "RFUD", "TRADEDATE": "2023-03-31", "SECID": "TYU3", "OPEN": null, "LOW": null, "HIGH": null, "CLOSE": null, "OPENPOSITIONVALUE": 46452.00, "VALUE": null, "VOLUME": null, "OPENPOSITION": 12, "SETTLEPRICE": 3.87100, "SWAPRATE": 0.00000, "WAPRICE": null, "SETTLEPRICEDAY": 3.93800, "CHANGE": null, "QTY": null, "NUMTRADES": 0},
{"BOARDID": "RFUD", "TRADEDATE": "2023-03-31", "SECID": "TYZ3", "OPEN": null, "LOW": null, "HIGH": null, "CLOSE": null, "OPENPOSITIONVALUE": 22314.00, "VALUE": null, "VOLUME": null, "OPENPOSITION": 6, "SETTLEPRICE": 3.71900, "SWAPRATE": 0.00000, "WAPRICE": null, "SETTLEPRICEDAY": 3.72300, "CHANGE": null, "QTY": null, "NUMTRADES": 0},
{"BOARDID": "RFUD", "TRADEDATE": "2023-03-31", "SECID": "UCH4", "OPEN": null, "LOW": null, "HIGH": null, "CLOSE": null, "OPENPOSITIONVALUE": 150073.12, "VALUE": null, "VOLUME": null, "OPENPOSITION": 2, "SETTLEPRICE": 6.65200, "SWAPRATE": 0.00000, "WAPRICE": null, "SETTLEPRICEDAY": 6.67300, "CHANGE": null, "QTY": null, "NUMTRADES": 0},
{"BOARDID": "RFUD", "TRADEDATE": "2023-03-31", "SECID": "UCM3", "OPEN": 6.85700, "LOW": 6.84000, "HIGH": 6.86400, "CLOSE": 6.84000, "OPENPOSITIONVALUE": 1410125901.00, "VALUE": 170406362.06, "VOLUME": 2205, "OPENPOSITION": 18276, "SETTLEPRICE": 6.84000, "SWAPRATE": 0.00000, "WAPRICE": 6.85100, "SETTLEPRICEDAY": 6.86200, "CHANGE": -0.29000, "QTY": 3, "NUMTRADES": 793},
{"BOARDID": "RFUD", "TRADEDATE": "2023-03-31", "SECID": "UCM3UCU3", "OPEN": null, "LOW": null, "HIGH": null, "CLOSE": null, "OPENPOSITIONVALUE": 0.00, "VALUE": null, "VOLUME": null, "OPENPOSITION": 0, "SETTLEPRICE": -0.08100, "SWAPRATE": null, "WAPRICE": null, "SETTLEPRICEDAY": -0.08200, "CHANGE": null, "QTY": null, "NUMTRADES": 0},
{"BOARDID": "RFUD", "TRADEDATE": "2023-03-31", "SECID": "UCU3", "OPEN": null, "LOW": null, "HIGH": null, "CLOSE": null, "OPENPOSITIONVALUE": 0.00, "VALUE": null, "VOLUME": null, "OPENPOSITION": 0, "SETTLEPRICE": 6.75900, "SWAPRATE": 0.00000, "WAPRICE": null, "SETTLEPRICEDAY": 6.78000, "CHANGE": null, "QTY": null, "NUMTRADES": 0},
{"BOARDID": "RFUD", "TRADEDATE": "2023-03-31", "SECID": "UCZ3", "OPEN": null, "LOW": null, "HIGH": null, "CLOSE": null, "OPENPOSITIONVALUE": 0.00, "VALUE": null, "VOLUME": null, "OPENPOSITION": 0, "SETTLEPRICE": 6.70100, "SWAPRATE": 0.00000, "WAPRICE": null, "SETTLEPRICEDAY": 6.72300, "CHANGE": null, "QTY": null, "NUMTRADES": 0},
{"BOARDID": "RFUD", "TRADEDATE": "2023-03-31", "SECID": "USDRUBF", "OPEN": 77.18000, "LOW": 77.09000, "HIGH": 77.98000, "CLOSE": 77.51000, "OPENPOSITIONVALUE": 13268588160.00, "VALUE": 1836528890.00, "VOLUME": 23687, "OPENPOSITION": 171296, "SETTLEPRICE": 77.46000, "SWAPRATE": 0.02881, "WAPRICE": 77.53000, "SETTLEPRICEDAY": 77.41000, "CHANGE": 0.39000, "QTY": 1, "NUMTRADES": 6297},
{"BOARDID": "RFUD", "TRADEDATE": "2023-03-31", "SECID": "USD_CLT", "OPEN": null, "LOW": null, "HIGH": null, "CLOSE": null, "OPENPOSITIONVALUE": 0.00, "VALUE": null, "VOLUME": null, "OPENPOSITION": 0, "SETTLEPRICE": 77.46000, "SWAPRATE": null, "WAPRICE": null, "SETTLEPRICEDAY": null, "CHANGE": null, "QTY": null, "NUMTRADES": 0},
{"BOARDID": "RFUD", "TRADEDATE": "2023-03-31", "SECID": "VBM3", "OPEN": 1867.00000, "LOW": 1817.00000, "HIGH": 1876.00000, "CLOSE": 1836.00000, "OPENPOSITIONVALUE": 976747596.00, "VALUE": 302605640.00, "VOLUME": 164253, "OPENPOSITION": 531708, "SETTLEPRICE": 1837.00000, "SWAPRATE": 0.00000, "WAPRICE": 1842.00000, "SETTLEPRICEDAY": 1828.00000, "CHANGE": -1.66000, "QTY": 1, "NUMTRADES": 13642},
{"BOARDID": "RFUD", "TRADEDATE": "2023-03-31", "SECID": "VBM3VBU3", "OPEN": null, "LOW": null, "HIGH": null, "CLOSE": null, "OPENPOSITIONVALUE": 0.00, "VALUE": null, "VOLUME": null, "OPENPOSITION": 0, "SETTLEPRICE": 23.00000, "SWAPRATE": null, "WAPRICE": null, "SETTLEPRICEDAY": 24.00000, "CHANGE": null, "QTY": null, "NUMTRADES": 0},
{"BOARDID": "RFUD", "TRADEDATE": "2023-03-31", "SECID": "VBU3", "OPEN": 1882.00000, "LOW": 1842.00000, "HIGH": 1898.00000, "CLOSE": 1864.00000, "OPENPOSITIONVALUE": 50309280.00, "VALUE": 11686531.00, "VOLUME": 6202, "OPENPOSITION": 27048, "SETTLEPRICE": 1860.00000, "SWAPRATE": 0.00000, "WAPRICE": 1884.00000, "SETTLEPRICEDAY": 1852.00000, "CHANGE": -1.17000, "QTY": 10, "NUMTRADES": 840},
{"BOARDID": "RFUD", "TRADEDATE": "2023-03-31", "SECID": "VBZ3", "OPEN": 1925.00000, "LOW": 1908.00000, "HIGH": 1925.00000, "CLOSE": 1908.00000, "OPENPOSITIONVALUE": 1242216.00, "VALUE": 17254.00, "VOLUME": 9, "OPENPOSITION": 648, "SETTLEPRICE": 1917.00000, "SWAPRATE": 0.00000, "WAPRICE": 1917.00000, "SETTLEPRICEDAY": 1908.00000, "CHANGE": -0.78000, "QTY": 1, "NUMTRADES": 7},
{"BOARDID": "RFUD", "TRADEDATE": "2023-03-31", "SECID": "VIJ3", "OPEN": null, "LOW": null, "HIGH": null, "CLOSE": null, "OPENPOSITIONVALUE": 951358.38, "VALUE": null, "VOLUME": null, "OPENPOSITION": 178, "SETTLEPRICE": 34.50000, "SWAPRATE": 0.00000, "WAPRICE": null, "SETTLEPRICEDAY": 34.50000, "CHANGE": null, "QTY": null, "NUMTRADES": 0},
{"BOARDID": "RFUD", "TRADEDATE": "2023-03-31", "SECID": "VIK3", "OPEN": null, "LOW": null, "HIGH": null, "CLOSE": null, "OPENPOSITIONVALUE": 0.00, "VALUE": null, "VOLUME": null, "OPENPOSITION": 0, "SETTLEPRICE": 34.50000, "SWAPRATE": 0.00000, "WAPRICE": null, "SETTLEPRICEDAY": 34.50000, "CHANGE": null, "QTY": null, "NUMTRADES": 0},
{"BOARDID": "RFUD", "TRADEDATE": "2023-03-31", "SECID": "VTBR_CLT", "OPEN": null, "LOW": null, "HIGH": null, "CLOSE": null, "OPENPOSITIONVALUE": 0.00, "VALUE": null, "VOLUME": null, "OPENPOSITION": 0, "SETTLEPRICE": 0.01808, "SWAPRATE": null, "WAPRICE": null, "SETTLEPRICEDAY": null, "CHANGE": null, "QTY": null, "NUMTRADES": 0},
{"BOARDID": "RFUD", "TRADEDATE": "2023-03-31", "SECID": "W4F4", "OPEN": null, "LOW": null, "HIGH": null, "CLOSE": null, "OPENPOSITIONVALUE": 59000.00, "VALUE": null, "VOLUME": null, "OPENPOSITION": 4, "SETTLEPRICE": 14750.00000, "SWAPRATE": 0.00000, "WAPRICE": null, "SETTLEPRICEDAY": 14750.00000, "CHANGE": null, "QTY": null, "NUMTRADES": 0},
{"BOARDID": "RFUD", "TRADEDATE": "2023-03-31", "SECID": "W4G4", "OPEN": null, "LOW": null, "HIGH": null, "CLOSE": null, "OPENPOSITIONVALUE": 0.00, "VALUE": null, "VOLUME": null, "OPENPOSITION": 0, "SETTLEPRICE": 14800.00000, "SWAPRATE": 0.00000, "WAPRICE": null, "SETTLEPRICEDAY": 14800.00000, "CHANGE": null, "QTY": null, "NUMTRADES": 0},
{"BOARDID": "RFUD", "TRADEDATE": "2023-03-31", "SECID": "W4H3", "OPEN": 13510.00000, "LOW": 13510.00000, "HIGH": 13580.00000, "CLOSE": 13580.00000, "OPENPOSITIONVALUE": 0.00, "VALUE": 256760.00, "VOLUME": 19, "OPENPOSITION": 0, "SETTLEPRICE": 13572.00000, "SWAPRATE": 0.00000, "WAPRICE": 13514.00000, "SETTLEPRICEDAY": 13520.00000, "CHANGE": 0.52000, "QTY": 1, "NUMTRADES": 6},
{"BOARDID": "RFUD", "TRADEDATE": "2023-03-31", "SECID": "W4H4", "OPEN": null, "LOW": null, "HIGH": null, "CLOSE": null, "OPENPOSITIONVALUE": 0.00, "VALUE": null, "VOLUME": null, "OPENPOSITION": 0, "SETTLEPRICE": 14910.00000, "SWAPRATE": 0.00000, "WAPRICE": null, "SETTLEPRICEDAY": 14910.00000, "CHANGE": null, "QTY": null, "NUMTRADES": 0},
{"BOARDID": "RFUD", "TRADEDATE": "2023-03-31", "SECID": "W4J3", "OPEN": 13690.00000, "LOW": 13660.00000, "HIGH": 13840.00000, "CLOSE": 13700.00000, "OPENPOSITIONVALUE": 4575800.00, "VALUE": 1069060.00, "VOLUME": 78, "OPENPOSITION": 334, "SETTLEPRICE": 13700.00000, "SWAPRATE": 0.00000, "WAPRICE": 13706.00000, "SETTLEPRICEDAY": 13700.00000, "CHANGE": 0.44000, "QTY": 6, "NUMTRADES": 21},
{"BOARDID": "RFUD", "TRADEDATE": "2023-03-31", "SECID": "W4K3", "OPEN": 13880.00000, "LOW": 13770.00000, "HIGH": 14070.00000, "CLOSE": 13940.00000, "OPENPOSITIONVALUE": 5185680.00, "VALUE": 1795530.00, "VOLUME": 129, "OPENPOSITION": 372, "SETTLEPRICE": 13940.00000, "SWAPRATE": 0.00000, "WAPRICE": 13919.00000, "SETTLEPRICEDAY": 13940.00000, "CHANGE": 0.22000, "QTY": 1, "NUMTRADES": 33},
{"BOARDID": "RFUD", "TRADEDATE": "2023-03-31", "SECID": "W4M3", "OPEN": 13950.00000, "LOW": 13940.00000, "HIGH": 14270.00000, "CLOSE": 14000.00000, "OPENPOSITIONVALUE": 75906180.00, "VALUE": 686280.00, "VOLUME": 49, "OPENPOSITION": 5418, "SETTLEPRICE": 14010.00000, "SWAPRATE": 0.00000, "WAPRICE": 14006.00000, "SETTLEPRICEDAY": 14000.00000, "CHANGE": 0.72000, "QTY": 6, "NUMTRADES": 27},
{"BOARDID": "RFUD", "TRADEDATE": "2023-03-31", "SECID": "W4M4", "OPEN": null, "LOW": null, "HIGH": null, "CLOSE": null, "OPENPOSITIONVALUE": 0.00, "VALUE": null, "VOLUME": null, "OPENPOSITION": 0, "SETTLEPRICE": 15360.00000, "SWAPRATE": 0.00000, "WAPRICE": null, "SETTLEPRICEDAY": 15360.00000, "CHANGE": null, "QTY": null, "NUMTRADES": 0},
{"BOARDID": "RFUD", "TRADEDATE": "2023-03-31", "SECID": "W4N3", "OPEN": null, "LOW": null, "HIGH": null, "CLOSE": null, "OPENPOSITIONVALUE": 28240.00, "VALUE": null, "VOLUME": null, "OPENPOSITION": 2, "SETTLEPRICE": 14120.00000, "SWAPRATE": 0.00000, "WAPRICE": null, "SETTLEPRICEDAY": 14120.00000, "CHANGE": null, "QTY": null, "NUMTRADES": 0},
{"BOARDID": "RFUD", "TRADEDATE": "2023-03-31", "SECID": "W4Q3", "OPEN": null, "LOW": null, "HIGH": null, "CLOSE": null, "OPENPOSITIONVALUE": 0.00, "VALUE": null, "VOLUME": null, "OPENPOSITION": 0, "SETTLEPRICE": 14200.00000, "SWAPRATE": 0.00000, "WAPRICE": null, "SETTLEPRICEDAY": 14200.00000, "CHANGE": null, "QTY": null, "NUMTRADES": 0},
{"BOARDID": "RFUD", "TRADEDATE": "2023-03-31", "SECID": "W4U3", "OPEN": null, "LOW": null, "HIGH": null, "CLOSE": null, "OPENPOSITIONVALUE": 28866600.00, "VALUE": null, "VOLUME": null, "OPENPOSITION": 2030, "SETTLEPRICE": 14220.00000, "SWAPRATE": 0.00000, "WAPRICE": null, "SETTLEPRICEDAY": 14220.00000, "CHANGE": null, "QTY": null, "NUMTRADES": 0},
{"BOARDID": "RFUD", "TRADEDATE": "2023-03-31", "SECID": "W4V3", "OPEN": null, "LOW": null, "HIGH": null, "CLOSE": null, "OPENPOSITIONVALUE": 0.00, "VALUE": null, "VOLUME": null, "OPENPOSITION": 0, "SETTLEPRICE": 14410.00000, "SWAPRATE": 0.00000, "WAPRICE": null, "SETTLEPRICEDAY": 14410.00000, "CHANGE": null, "QTY": null, "NUMTRADES": 0},
{"BOARDID": "RFUD", "TRADEDATE": "2023-03-31", "SECID": "W4X3", "OPEN": null, "LOW": null, "HIGH": null, "CLOSE": null, "OPENPOSITIONVALUE": 0.00, "VALUE": null, "VOLUME": null, "OPENPOSITION": 0, "SETTLEPRICE": 14510.00000, "SWAPRATE": 0.00000, "WAPRICE": null, "SETTLEPRICEDAY": 14510.00000, "CHANGE": null, "QTY": null, "NUMTRADES": 0},
{"BOARDID": "RFUD", "TRADEDATE": "2023-03-31", "SECID": "W4Z3", "OPEN": null, "LOW": null, "HIGH": null, "CLOSE": null, "OPENPOSITIONVALUE": 29622500.00, "VALUE": null, "VOLUME": null, "OPENPOSITION": 2050, "SETTLEPRICE": 14450.00000, "SWAPRATE": 0.00000, "WAPRICE": null, "SETTLEPRICEDAY": 14450.00000, "CHANGE": null, "QTY": null, "NUMTRADES": 0},
{"BOARDID": "RFUD", "TRADEDATE": "2023-03-31", "SECID": "YNDX_CLT", "OPEN": null, "LOW": null, "HIGH": null, "CLOSE": null, "OPENPOSITIONVALUE": 0.00, "VALUE": null, "VOLUME": null, "OPENPOSITION": 0, "SETTLEPRICE": 1894.60000, "SWAPRATE": null, "WAPRICE": null, "SETTLEPRICEDAY": null, "CHANGE": null, "QTY": null, "NUMTRADES": 0},
{"BOARDID": "RFUD", "TRADEDATE": "2023-03-31", "SECID": "YNM3", "OPEN": 19455.00000, "LOW": 19204.00000, "HIGH": 19517.00000, "CLOSE": 19280.00000, "OPENPOSITIONVALUE": 582917632.00, "VALUE": 102442895.00, "VOLUME": 5299, "OPENPOSITION": 30272, "SETTLEPRICE": 19256.00000, "SWAPRATE": 0.00000, "WAPRICE": 19332.00000, "SETTLEPRICEDAY": 19276.00000, "CHANGE": -0.86000, "QTY": 7, "NUMTRADES": 2170},
{"BOARDID": "RFUD", "TRADEDATE": "2023-03-31", "SECID": "YNM3YNU3", "OPEN": null, "LOW": null, "HIGH": null, "CLOSE": null, "OPENPOSITIONVALUE": 0.00, "VALUE": null, "VOLUME": null, "OPENPOSITION": 0, "SETTLEPRICE": 415.00000, "SWAPRATE": null, "WAPRICE": null, "SETTLEPRICEDAY": 380.00000, "CHANGE": null, "QTY": null, "NUMTRADES": 0},
{"BOARDID": "RFUD", "TRADEDATE": "2023-03-31", "SECID": "YNU3", "OPEN": 19861.00000, "LOW": 19600.00000, "HIGH": 19885.00000, "CLOSE": 19720.00000, "OPENPOSITIONVALUE": 35093064.00, "VALUE": 1202036.00, "VOLUME": 61, "OPENPOSITION": 1784, "SETTLEPRICE": 19671.00000, "SWAPRATE": 0.00000, "WAPRICE": 19706.00000, "SETTLEPRICEDAY": 19656.00000, "CHANGE": -1.12000, "QTY": 1, "NUMTRADES": 45},
{"BOARDID": "RFUD", "TRADEDATE": "2023-03-31", "SECID": "YNZ3", "OPEN": null, "LOW": null, "HIGH": null, "CLOSE": null, "OPENPOSITIONVALUE": 0.00, "VALUE": null, "VOLUME": null, "OPENPOSITION": 0, "SETTLEPRICE": 20047.00000, "SWAPRATE": 0.00000, "WAPRICE": null, "SETTLEPRICEDAY": 20057.00000, "CHANGE": null, "QTY": null, "NUMTRADES": 0},
{"BOARDID": "RFUD", "TRADEDATE": "2023-03-31", "SECID": "ZnJ3", "OPEN": null, "LOW": null, "HIGH": null, "CLOSE": null, "OPENPOSITIONVALUE": 0.00, "VALUE": null, "VOLUME": null, "OPENPOSITION": 0, "SETTLEPRICE": 2898.50000, "SWAPRATE": 0.00000, "WAPRICE": null, "SETTLEPRICEDAY": 2898.50000, "CHANGE": null, "QTY": null, "NUMTRADES": 0},
{"BOARDID": "RFUD", "TRADEDATE": "2023-03-31", "SECID": "ZnJ3ZnK3", "OPEN": null, "LOW": null, "HIGH": null, "CLOSE": null, "OPENPOSITIONVALUE": 0.00, "VALUE": null, "VOLUME": null, "OPENPOSITION": 0, "SETTLEPRICE": -9.00000, "SWAPRATE": null, "WAPRICE": null, "SETTLEPRICEDAY": -9.50000, "CHANGE": null, "QTY": null, "NUMTRADES": 0},
{"BOARDID": "RFUD", "TRADEDATE": "2023-03-31", "SECID": "ZnK3", "OPEN": null, "LOW": null, "HIGH": null, "CLOSE": null, "OPENPOSITIONVALUE": 0.00, "VALUE": null, "VOLUME": null, "OPENPOSITION": 0, "SETTLEPRICE": 2889.50000, "SWAPRATE": 0.00000, "WAPRICE": null, "SETTLEPRICEDAY": 2889.00000, "CHANGE": null, "QTY": null, "NUMTRADES": 0},
{"BOARDID": "RFUD", "TRADEDATE": "2023-03-31", "SECID": "ZnM3", "OPEN": null, "LOW": null, "HIGH": null, "CLOSE": null, "OPENPOSITIONVALUE": 0.00, "VALUE": null, "VOLUME": null, "OPENPOSITION": 0, "SETTLEPRICE": 2882.00000, "SWAPRATE": 0.00000, "WAPRICE": null, "SETTLEPRICEDAY": 2880.50000, "CHANGE": null, "QTY": null, "NUMTRADES": 0}
]
],
"history.cursor": [
{
	"metadata": {
		"INDEX": {"type": "int64"},
		"TOTAL": {"type": "int64"},
		"PAGESIZE": {"type": "int64"}
	}
},
[
{"INDEX": 400, "TOTAL": 446, "PAGESIZE": 100}
]
]}
]